setup.py
ar_virtualenv_api.egg-info/PKG-INFO
ar_virtualenv_api.egg-info/SOURCES.txt
ar_virtualenv_api.egg-info/dependency_links.txt
ar_virtualenv_api.egg-info/top_level.txt
virtualenvapi/__init__.py
virtualenvapi/exceptions.py
virtualenvapi/manage.py
virtualenvapi/util.py