Metadata-Version: 1.0
Name: ar-virtualenv-api
Version: 2.0.0
Summary: An API for virtualenv/pip
Home-page: https://github.com/arteria/ar-virtualenv-api
Author: arteria GmbH
Author-email: admin@arteria.ch
License: BSD
Platform: UNKNOWN
